MANIFEST.in
README.rst
requirements.txt
setup.py
django_sanction/__init__.py
django_sanction/backends.py
django_sanction/models.py
django_sanction/tests.py
django_sanction/urls.py
django_sanction/views.py
django_sanction.egg-info/PKG-INFO
django_sanction.egg-info/SOURCES.txt
django_sanction.egg-info/dependency_links.txt
django_sanction.egg-info/requires.txt
django_sanction.egg-info/top_level.txt