Metadata-Version: 1.1
Name: django-sanction
Version: 0.3.1
Summary: A Django front end for the sanction OAuth2 client library
Home-page: https://github.com/demianbrecht/django-sanction
Author: Demian Brecht
Author-email: demianbrecht@gmail.com
License: MIT
Download-URL: https://github.com/demianbrecht/django-sanction
Keywords: python,oauth2,sanction,django
Platform: UNKNOWN
Classifier: Development Status :: 4 - Beta
Classifier: Environment :: Web Environment
Classifier: Intended Audience :: Developers
Classifier: License :: OSI Approved :: MIT License
Classifier: Natural Language :: English
Classifier: Programming Language :: Python
Classifier: Topic :: Internet :: WWW/HTTP
Classifier: Topic :: Internet :: WWW/HTTP :: Site Management
Classifier: Topic :: Software Development :: Libraries :: Python Modules
Classifier: Topic :: System :: Systems Administration :: Authentication/Directory
